dolze_templates/__init__.py
dolze_templates/asset-registry.json
dolze_templates/asset_manager.py
dolze_templates/navigation_manager.py
dolze_templates/page_manager.py
dolze_templates/sample.json
dolze_templates/template_manager.py
dolze_templates/template_registry.py
dolze_templates/ui_component_manager.py
dolze_templates/assets/global/base.css
dolze_templates/assets/global/base.js
dolze_templates/templates/layouts/template.html
dolze_templates/templates/sections/about/v1.html
dolze_templates/templates/sections/about/v10.html
dolze_templates/templates/sections/about/v2.html
dolze_templates/templates/sections/about/v3.html
dolze_templates/templates/sections/about/v4.html
dolze_templates/templates/sections/about/v5.html
dolze_templates/templates/sections/about/v6.html
dolze_templates/templates/sections/about/v7.html
dolze_templates/templates/sections/about/v8.html
dolze_templates/templates/sections/blog/v10.html
dolze_templates/templates/sections/blog/v7.html
dolze_templates/templates/sections/challenges/v1.html
dolze_templates/templates/sections/challenges/v10.html
dolze_templates/templates/sections/challenges/v2.html
dolze_templates/templates/sections/challenges/v3.html
dolze_templates/templates/sections/challenges/v4.html
dolze_templates/templates/sections/challenges/v5.html
dolze_templates/templates/sections/challenges/v6.html
dolze_templates/templates/sections/challenges/v7.html
dolze_templates/templates/sections/challenges/v8.html
dolze_templates/templates/sections/challenges/v9.html
dolze_templates/templates/sections/community/v1.html
dolze_templates/templates/sections/community/v10.html
dolze_templates/templates/sections/community/v2.html
dolze_templates/templates/sections/community/v3.html
dolze_templates/templates/sections/community/v4.html
dolze_templates/templates/sections/community/v4.js
dolze_templates/templates/sections/community/v5.html
dolze_templates/templates/sections/community/v6.html
dolze_templates/templates/sections/community/v7.html
dolze_templates-2.1.3.dist-info/licenses/LICENSE
dolze_templates-2.1.3.dist-info/METADATA
dolze_templates-2.1.3.dist-info/WHEEL
dolze_templates-2.1.3.dist-info/top_level.txt
dolze_templates-2.1.3.dist-info/RECORD
