Metadata-Version: 2.4
Name: dolze-templates
Version: 2.1.3
Summary: Template system for Dolze landing pages
Author-email: Dolze Team <info@dolze.com>
Project-URL: Homepage, https://github.com/dolze/dolze-templates
Project-URL: Bug Tracker, https://github.com/dolze/dolze-templates/issues
Classifier: Programming Language :: Python :: 3
Classifier: License :: OSI Approved :: MIT License
Classifier: Operating System :: OS Independent
Requires-Python: >=3.8
License-File: LICENSE
Requires-Dist: jinja2>=3.0.0
Dynamic: license-file
